task_scheduler/__init__.py
task_scheduler/cli.py
task_scheduler/interactive_mode.py
task_scheduler/main.py
task_scheduler/periodic_scheduling.py
task_scheduler/scheduler.py
task_scheduler/storage.py
task_scheduler/task.py
task_scheduler/time_slot.py
task_scheduler/utils.py
task_scheduler/visualisation.py
task_scheduler_x-3.0.3.dist-info/METADATA
task_scheduler_x-3.0.3.dist-info/WHEEL
task_scheduler_x-3.0.3.dist-info/entry_points.txt
task_scheduler_x-3.0.3.dist-info/top_level.txt
task_scheduler_x-3.0.3.dist-info/RECORD
