Metadata-Version: 2.1
Name: task-scheduler-x
Version: 3.0.3
Summary: A CLI-based Task Scheduling Application
Home-page: https://github.com/longauer/task_scheduler
Author: Samuel Longauer
Author-email: samuel.longauer@gmail.com
Classifier: Programming Language :: Python :: 3
Classifier: License :: OSI Approved :: MIT License
Classifier: Operating System :: OS Independent
Requires-Python: >=3.10
Requires-Dist: argparse
Requires-Dist: datetime
Requires-Dist: colorama
Requires-Dist: urwid
